package/__init__.py
package/topsis.py
TaritTopsis-1.0.0.dist-info/LICENSE.txt
TaritTopsis-1.0.0.dist-info/METADATA
TaritTopsis-1.0.0.dist-info/WHEEL
TaritTopsis-1.0.0.dist-info/top_level.txt
TaritTopsis-1.0.0.dist-info/RECORD
