Metadata-Version: 2.1
Name: TaritTopsis
Version: 1.0.0
Summary: TOPSIS for MCDM
Home-page: https://github.com/taritkandpal/TOPSIS-for-MCDM
Author: Tarit Kandpal
Author-email: taritkandpal@gmail.com
License: UNKNOWN
Platform: UNKNOWN
Classifier: Programming Language :: Python :: 3
Classifier: License :: OSI Approved :: MIT License
Classifier: Operating System :: OS Independent
Requires-Python: >=3.6
